<?xml version="1.0" encoding="utf-8"?>
<search>
  
  
  
  <entry>
    <title>HMCL启动器无法下载依赖的问题</title>
    <link href="/2026/05/07/HMCL%E5%90%AF%E5%8A%A8%E5%99%A8%E6%97%A0%E6%B3%95%E4%B8%8B%E8%BD%BD%E4%BE%9D%E8%B5%96%E7%9A%84%E9%97%AE%E9%A2%98/"/>
    <url>/2026/05/07/HMCL%E5%90%AF%E5%8A%A8%E5%99%A8%E6%97%A0%E6%B3%95%E4%B8%8B%E8%BD%BD%E4%BE%9D%E8%B5%96%E7%9A%84%E9%97%AE%E9%A2%98/</url>
    
    <content type="html"><![CDATA[<figure class="highlight"><table><tr><td class="gutter"><pre><span class="line">1</span><br></pre></td><td class="code"><pre><code class="hljs">系统：ArchLinux<br></code></pre></td></tr></table></figure><p><img src="/_posts/HMCL%E5%90%AF%E5%8A%A8%E5%99%A8%E6%97%A0%E6%B3%95%E4%B8%8B%E8%BD%BD%E4%BE%9D%E8%B5%96%E7%9A%84%E9%97%AE%E9%A2%98/%E6%9C%AA%E8%83%BD%E4%B8%8B%E8%BD%BD%E6%B8%B8%E6%88%8F%E4%BE%9D%E8%B5%96.png" alt="未能下载游戏依赖" title="未能下载游戏依赖"></p><p>奇奇怪怪的问题  又是权限问题呢~</p><p>直接&#96;sudo&#96;&#96;就好啦~</p>]]></content>
    
    
    <categories>
      
      <category>Minecraft</category>
      
    </categories>
    
    
    <tags>
      
      <tag>MC</tag>
      
      <tag>HMCL</tag>
      
      <tag>启动器</tag>
      
    </tags>
    
  </entry>
  
  
  
  <entry>
    <title>STM32CubeMX在Linux下只有X11模式才能正常工作</title>
    <link href="/2026/05/07/STM32CubeMX%E5%9C%A8Linux%E4%B8%8B%E5%8F%AA%E6%9C%89X11%E6%A8%A1%E5%BC%8F%E6%89%8D%E8%83%BD%E6%AD%A3%E5%B8%B8%E5%B7%A5%E4%BD%9C/"/>
    <url>/2026/05/07/STM32CubeMX%E5%9C%A8Linux%E4%B8%8B%E5%8F%AA%E6%9C%89X11%E6%A8%A1%E5%BC%8F%E6%89%8D%E8%83%BD%E6%AD%A3%E5%B8%B8%E5%B7%A5%E4%BD%9C/</url>
    
    <content type="html"><![CDATA[<p>最近想在Linux下折腾stm32，我用的是 <code>Arch + Niri</code> 的组合，直接打开CubeMX的话，会有界面大小不匹配和白屏的问题</p><p><del>装了gnome就正常了，因为这种完整的桌面环境对显示模式的控制更完善</del></p><p>这是因为CubeMX对Wayland支持并不完善，需要设置以xWayland运行</p><p>在启动脚本中加入<code>GDK_BACKEND=x11</code></p><p><em>选择完善的桌面环境(比如KDE gnome)则可以避免此问题</em></p>]]></content>
    
    
    <categories>
      
      <category>Linux</category>
      
    </categories>
    
    
    <tags>
      
      <tag>ArchLinux</tag>
      
      <tag>CubeMX</tag>
      
      <tag>Niri</tag>
      
      <tag>XWayland</tag>
      
    </tags>
    
  </entry>
  
  
  
  <entry>
    <title>ArchLinux下的串口设备权限管理：&#39;uucp&#39;组</title>
    <link href="/2026/05/07/ArchLinux%E4%B8%8B%E7%9A%84%E4%B8%B2%E5%8F%A3%E8%AE%BE%E5%A4%87%E6%9D%83%E9%99%90%E7%AE%A1%E7%90%86%EF%BC%9A-uucp-%E7%BB%84/"/>
    <url>/2026/05/07/ArchLinux%E4%B8%8B%E7%9A%84%E4%B8%B2%E5%8F%A3%E8%AE%BE%E5%A4%87%E6%9D%83%E9%99%90%E7%AE%A1%E7%90%86%EF%BC%9A-uucp-%E7%BB%84/</url>
    
    <content type="html"><![CDATA[<p><del>踩坑日记</del></p><h2 id="在使用串口调试助手的时候，一直连不上串口设备。【权限问题】"><a href="#在使用串口调试助手的时候，一直连不上串口设备。【权限问题】" class="headerlink" title="在使用串口调试助手的时候，一直连不上串口设备。【权限问题】"></a>在使用串口调试助手的时候，一直连不上串口设备。【权限问题】</h2><h1 id="解决：将用户加入uucp用户组"><a href="#解决：将用户加入uucp用户组" class="headerlink" title="解决：将用户加入uucp用户组"></a>解决：将用户加入uucp用户组</h1><p><code>sudo usermod -aG uucp $USER</code></p><table><thead><tr><th>组</th><th>影响文件</th><th>作用</th></tr></thead><tbody><tr><td>uucp</td><td>&#x2F;dev&#x2F;ttyS[0-9]+, &#x2F;dev&#x2F;tts&#x2F;[0-9]+, &#x2F;dev&#x2F;ttyUSB[0-9]+, &#x2F;dev&#x2F;ttyACM[0-9]+, &#x2F;dev&#x2F;rfcomm[0-9]+</td><td>串口和 USB 设备，例如猫、手柄 RS-232&#x2F;串口。</td></tr></tbody></table><p>对于其它组的作用，可见Archwiki<a href="https://wiki.archlinuxcn.org/wiki/%E7%94%A8%E6%88%B7%E5%92%8C%E7%94%A8%E6%88%B7%E7%BB%84#%E7%BE%A4%E7%BB%84%E5%88%97%E8%A1%A8" title="群组列表">用户和用户组</a></p><p><em>值得一提的是，Arch中并没有dialout这个组。</em></p><h1 id="参考"><a href="#参考" class="headerlink" title="参考"></a>参考</h1><p><a href="https://bbs.archlinux.org/viewtopic.php?id=222093">ArchLinux Forums</a></p>]]></content>
    
    
    <categories>
      
      <category>Linux</category>
      
    </categories>
    
    
    <tags>
      
      <tag>ArchLinux</tag>
      
      <tag>串口设备</tag>
      
      <tag>stm32</tag>
      
      <tag>用户组</tag>
      
    </tags>
    
  </entry>
  
  
  
  <entry>
    <title>《围城》</title>
    <link href="/2026/04/15/%E3%80%8A%E5%9B%B4%E5%9F%8E%E3%80%8B/"/>
    <url>/2026/04/15/%E3%80%8A%E5%9B%B4%E5%9F%8E%E3%80%8B/</url>
    
    <content type="html"><![CDATA[<blockquote><p><strong>《围城》好像一面镜子，照出了我内心的“方鸿渐”</strong></p></blockquote>]]></content>
    
    
    <categories>
      
      <category>文学</category>
      
    </categories>
    
    
    <tags>
      
      <tag>《围城》</tag>
      
    </tags>
    
  </entry>
  
  
  
  <entry>
    <title>SSH更新系统的正确方式：使用Tmux</title>
    <link href="/2026/03/25/SSH%E6%9B%B4%E6%96%B0%E7%B3%BB%E7%BB%9F%E7%9A%84%E6%AD%A3%E7%A1%AE%E6%96%B9%E5%BC%8F%EF%BC%9A%E4%BD%BF%E7%94%A8Tmux/"/>
    <url>/2026/03/25/SSH%E6%9B%B4%E6%96%B0%E7%B3%BB%E7%BB%9F%E7%9A%84%E6%AD%A3%E7%A1%AE%E6%96%B9%E5%BC%8F%EF%BC%9A%E4%BD%BF%E7%94%A8Tmux/</url>
    
    <content type="html"><![CDATA[<p>在SSH远程更新Arch的过程中，由于连接断开造成了内核损坏，这次经历让我明白了应该在Tmux中执行更新。</p><h1 id="报错"><a href="#报错" class="headerlink" title="报错"></a>报错</h1><figure class="highlight subunit"><table><tr><td class="gutter"><pre><span class="line">1</span><br><span class="line">2</span><br></pre></td><td class="code"><pre><code class="hljs subunit"><span class="hljs-keyword">error: </span>file &#x27;/vmlinuz-linux&#x27; not found<br>you need to load the kernel first<br></code></pre></td></tr></table></figure><h1 id="修复（使用ArchLinux-ISO）"><a href="#修复（使用ArchLinux-ISO）" class="headerlink" title="修复（使用ArchLinux ISO）"></a>修复（使用ArchLinux ISO）</h1><ol><li>进入Live环境</li><li>挂载分区<blockquote><p>mount &#x2F;dev&#x2F;sda2 &#x2F;mnt</p></blockquote></li><li>进入系统<blockquote><p>arch-chroot &#x2F;mnt</p></blockquote></li><li>重新安装内核<blockquote><p>pacman -S linux linux-firmware</p></blockquote></li><li>手动重建grub（可选）<blockquote><p>grub-install &#x2F;dev&#x2F;sda  grub-mkconfig -o &#x2F;boot&#x2F;grub&#x2F;grub.cfg</p></blockquote></li><li>重启<blockquote><p>exit<br>umount -R &#x2F;mnt<br>reboot</p></blockquote></li></ol><h1 id="使用Tmux更新系统"><a href="#使用Tmux更新系统" class="headerlink" title="使用Tmux更新系统"></a>使用Tmux更新系统</h1><h2 id="安装"><a href="#安装" class="headerlink" title="安装"></a>安装</h2><blockquote><p>pacman -S tmux</p></blockquote><h2 id="使用"><a href="#使用" class="headerlink" title="使用"></a>使用</h2><ol><li>新建Tmux会话<blockquote><p>tmux</p></blockquote></li><li>更新系统</li></ol><h1 id="引用"><a href="#引用" class="headerlink" title="引用"></a>引用</h1><ul><li>关于Tmux的详细信息 <a href="Tmux-ArchWiki">https://wiki.archlinuxcn.org/wiki/Tmux</a></li><li>Tmux的仓库 <a href="Tmux-Github">https://github.com/tmux/tmux</a></li></ul>]]></content>
    
    
    <categories>
      
      <category>Linux</category>
      
    </categories>
    
    
    <tags>
      
      <tag>ArchLinux</tag>
      
      <tag>SSH</tag>
      
      <tag>Tmux</tag>
      
    </tags>
    
  </entry>
  
  
  
  
</search>
